vendetect/__init__.py
vendetect/__main__.py
vendetect/_cli.py
vendetect/comparison.py
vendetect/copydetect.py
vendetect/detector.py
vendetect/diffing.py
vendetect/errors.py
vendetect/py.typed
vendetect/repo.py
vendetect-0.0.2.dist-info/METADATA
vendetect-0.0.2.dist-info/WHEEL
vendetect-0.0.2.dist-info/entry_points.txt
vendetect-0.0.2.dist-info/licenses/LICENSE
vendetect-0.0.2.dist-info/RECORD
