Metadata-Version: 2.4
Name: vendetect
Version: 0.0.2
Summary: Command-line tool for automatically detecting vendored and copy/pasted code
Project-URL: Homepage, https://pypi.org/project/vendetect
Project-URL: Documentation, https://trailofbits.github.io/vendetect/
Project-URL: Issues, https://github.com/trailofbits/vendetect/issues
Project-URL: Source, https://github.com/trailofbits/vendetect
Author-email: Trail of Bits <opensource@trailofbits.com>
License: 
License-File: LICENSE
Classifier: License :: OSI Approved :: GNU Affero General Public License v3 or later (AGPLv3+)
Classifier: Programming Language :: Python :: 3
Requires-Python: >=3.11
Requires-Dist: copydetect>=0.5.0
Requires-Dist: rich>=14.0.0
